protoc_gen_connectrpc/__init__.py
protoc_gen_connect_python-0.7.1.data/scripts/protoc-gen-connect-python
protoc_gen_connect_python-0.7.1.dist-info/WHEEL
protoc_gen_connect_python-0.7.1.dist-info/METADATA
protoc_gen_connect_python-0.7.1.dist-info/RECORD
