Metadata-Version: 2.4
Name: protoc-gen-connect-python
Version: 0.7.1
Summary: Code generator for connect-python
Keywords: protoc,protobuf,protocol-buffers,code-generation,connect,connectrpc,connect-protocol,connect-rpc,rpc,compiler,plugin
Classifier: Development Status :: 3 - Alpha
Classifier: Environment :: Console
Classifier: Intended Audience :: Developers
Classifier: License :: OSI Approved :: Apache Software License
Classifier: Operating System :: OS Independent
Classifier: Programming Language :: Go
Classifier: Programming Language :: Python :: 3
Classifier: Programming Language :: Python :: 3 :: Only
Classifier: Programming Language :: Python :: 3.10
Classifier: Programming Language :: Python :: 3.11
Classifier: Programming Language :: Python :: 3.12
Classifier: Programming Language :: Python :: 3.13
Classifier: Topic :: Software Development :: Code Generators
Classifier: Topic :: Software Development :: Compilers
Classifier: Topic :: System :: Networking
Maintainer: Anuraag Agrawal, Spencer Nelson, Stefan VanBuren, Yasushi Itoh
Maintainer-email: Anuraag Agrawal <anuraaga@gmail.com>, Spencer Nelson <spencer@firetiger.com>, Stefan VanBuren <svanburen@buf.build>, Yasushi Itoh <i2y.may.roku@gmail.com>
Requires-Python: >=3.10
Project-URL: Homepage, https://github.com/connectrpc/connect-python
Project-URL: Issues, https://github.com/connectrpc/connect-python/issues
Project-URL: Repository, https://github.com/connectrpc/connect-python
